percolate/__init__.py
percolate/__version__
percolate/api/__init__.py
percolate/api/auth/__init__.py
percolate/api/auth/jwt_provider.py
percolate/api/auth/middleware.py
percolate/api/auth/models.py
percolate/api/auth/providers.py
percolate/api/auth/server.py
percolate/api/auth/utils.py
percolate/api/controllers/__init__.py
percolate/api/controllers/audio.py
percolate/api/controllers/memory.py
percolate/api/controllers/oauth.py
percolate/api/controllers/resource_creator.py
percolate/api/controllers/tus.py
percolate/api/controllers/tus_filesystem.py
percolate/api/docs/audio_processing.md
percolate/api/docs/content_bookmark.md
percolate/api/docs/content_upload.md
percolate/api/docs/memory_proxy.md
percolate/api/docs/scheduled_tasks.md
percolate/api/docs/secure_file_store.md
percolate/api/examples/client_examples.py
percolate/api/examples/sample.txt
percolate/api/main.py
percolate/api/mcp_server/README.md
percolate/api/mcp_server/__init__.py
percolate/api/mcp_server/__main__.py
percolate/api/mcp_server/api_repository.py
percolate/api/mcp_server/app.py
percolate/api/mcp_server/auth.py
percolate/api/mcp_server/base_repository.py
percolate/api/mcp_server/config.py
percolate/api/mcp_server/database_repository.py
percolate/api/mcp_server/exceptions.py
percolate/api/mcp_server/integration.py
percolate/api/mcp_server/pytest.ini
percolate/api/mcp_server/repository_factory.py
percolate/api/mcp_server/server.py
percolate/api/mcp_server/tools/__init__.py
percolate/api/mcp_server/tools/chat_tools.py
percolate/api/mcp_server/tools/entity_tools.py
percolate/api/mcp_server/tools/file_tools.py
percolate/api/mcp_server/tools/function_tools.py
percolate/api/mcp_server/tools/help_tools.py
percolate/api/mcp_server/tools/memory_tools.py
percolate/api/mcp_server/utils.py
percolate/api/routes/__init__.py
percolate/api/routes/admin/__init__.py
percolate/api/routes/admin/router.py
percolate/api/routes/audio/Readme.md
percolate/api/routes/audio/__init__.py
percolate/api/routes/audio/router.py
percolate_db-0.3.5.dist-info/METADATA
percolate_db-0.3.5.dist-info/WHEEL
percolate_db-0.3.5.dist-info/entry_points.txt
percolate_db-0.3.5.dist-info/RECORD
